tailscale/__init__.py
tailscale/exceptions.py
tailscale/models.py
tailscale/py.typed
tailscale/tailscale.py
tailscale_nuevo-1.0.0.dist-info/LICENSE.md
tailscale_nuevo-1.0.0.dist-info/METADATA
tailscale_nuevo-1.0.0.dist-info/WHEEL
tailscale_nuevo-1.0.0.dist-info/RECORD
