Metadata-Version: 2.1
Name: tailscale-nuevo
Version: 1.0.0
Summary: Asynchronous client for the Tailscale API.
Home-page: https://github.com/offbyone/python-tailscale
License: MIT
Keywords: tailscale,vpn,wireguard,api,async,client
Author: Franck Nijhof
Author-email: opensource@frenck.dev
Maintainer: Chris Rose
Maintainer-email: offline@offby1.net
Requires-Python: >=3.9,<4.0
Classifier: Development Status :: 5 - Production/Stable
Classifier: Framework :: AsyncIO
Classifier: Intended Audience :: Developers
Classifier: License :: OSI Approved :: MIT License
Classifier: Natural Language :: English
Classifier: Programming Language :: Python :: 3
Classifier: Programming Language :: Python :: 3.9
Classifier: Programming Language :: Python :: 3.10
Classifier: Programming Language :: Python :: 3.11
Classifier: Topic :: Software Development :: Libraries :: Python Modules
Requires-Dist: aiohttp (>=3.0.0)
Requires-Dist: pydantic (>=1.8,<3.0)
Requires-Dist: yarl (>=1.6.0)
Project-URL: Bug Tracker, https://github.com/offbyone/python-tailscale/issues
Project-URL: Changelog, https://github.com/offbyone/python-tailscale/releases
Project-URL: Documentation, https://github.com/offbyone/python-tailscale
Project-URL: Repository, https://github.com/offbyone/python-tailscale
